autoderm/__init__.py
autoderm/api_call.py
autoderm/client.py
autoderm/client_base.py
autoderm/constants.py
autoderm/exceptions.py
autoderm-0.0.5.dist-info/LICENSE
autoderm-0.0.5.dist-info/METADATA
autoderm-0.0.5.dist-info/WHEEL
autoderm-0.0.5.dist-info/RECORD
