Metadata-Version: 2.1
Name: autoderm
Version: 0.0.5
Summary: Autoderm's Official SDK Client.
Author: Lucas
Author-email: lucas@autoderm.ai
Requires-Python: >=3.9,<4.0
Classifier: Programming Language :: Python :: 3
Classifier: Programming Language :: Python :: 3.9
Classifier: Programming Language :: Python :: 3.10
Classifier: Programming Language :: Python :: 3.11
Classifier: Programming Language :: Python :: 3.12
Requires-Dist: httpx (>=0.25,<0.26)
Requires-Dist: orjson (>=3.9.10,<4.0.0)
